i3e2e/__init__.py
vorpal/BaseHttpEndpoint.py
vorpal/ElementWrapper.py
vorpal/__init__.py
vorpal/Base/__init__.py
vorpal/Base/base_http_endpoint.py
vorpal/Base/custom_selenium_driver.py
vorpal/Base/decorators.py
vorpal/Base/element.py
vorpal/Base/expected_condition.py
vorpal/Base/page.py
vorpal/Base/webdriver_factory.py
vorpal-3.4.2.dist-info/METADATA
vorpal-3.4.2.dist-info/RECORD
vorpal-3.4.2.dist-info/WHEEL
vorpal-3.4.2.dist-info/top_level.txt
