Metadata-Version: 2.1
Name: vorpal
Version: 3.4.2
Summary: End-to-end testing framework
Home-page: UNKNOWN
Author: i3logix, LLC
Author-email: cemerson@i3logix.com
License: MIT
Project-URL: Owner, http://i3logix.com
Keywords: test automation qa
Platform: UNKNOWN
Classifier: Development Status :: 3 - Alpha
Classifier: License :: OSI Approved :: MIT License
Classifier: Programming Language :: Python :: 3.6
Requires-Python: >=3.6
Requires-Dist: selenium
Requires-Dist: requests
